libptsd/__init__.py
libptsd/dummy.py
libptsd-0.1.4.dist-info/LICENSE
libptsd-0.1.4.dist-info/METADATA
libptsd-0.1.4.dist-info/WHEEL
libptsd-0.1.4.dist-info/top_level.txt
libptsd-0.1.4.dist-info/RECORD
