Metadata-Version: 2.1
Name: libptsd
Version: 0.1.4
Summary: A new standard library for programmers that has PTSD with their projects.
Author-email: Khyle Isaias <khyleisaias@gmail.com>
License: Copyright 2022, Khyle Isaias <khyleisaias@gmail.com>        
Project-URL: Homepage, https://github.com/kernelk14/ptsd
Project-URL: Bug Tracker, https://github.com/kernelk14/ptsd/issues
Classifier: Programming Language :: Python :: 3
Classifier: License :: OSI Approved :: MIT License
Classifier: Operating System :: OS Independent
Requires-Python: >=3.6
License-File: LICENSE
